chatsynth_vanshajr/__init__.py
chatsynth_vanshajr/chat_preview.py
chatsynth_vanshajr/faiss_creator.py
chatsynth_vanshajr/github_deploy.py
chatsynth_vanshajr/json_creator.py
chatsynth_vanshajr/retriever.py
chatsynth_vanshajr-0.6.0.dist-info/METADATA
chatsynth_vanshajr-0.6.0.dist-info/WHEEL
chatsynth_vanshajr-0.6.0.dist-info/top_level.txt
chatsynth_vanshajr-0.6.0.dist-info/RECORD
