Metadata-Version: 2.4
Name: chatsynth_vanshajr
Version: 0.6.0
Summary: A library for creating and deploying chatbots with FAISS and GitHub integration for the ChatSynth app: https://chatsynth.streamlit.app.
Home-page: https://github.com/VanshajR/chatsynth_vanshajr
Author: Vanshaj Raghuvanshi
Author-email: vanshajraghuvanshi@gmail.com
Classifier: Programming Language :: Python :: 3
Classifier: License :: OSI Approved :: BSD License
Classifier: Operating System :: OS Independent
Requires-Python: >=3.8
Requires-Dist: streamlit
Requires-Dist: langchain
Requires-Dist: langchain-community
Requires-Dist: langchain-groq
Requires-Dist: langchain-huggingface
Requires-Dist: requests
Dynamic: author
Dynamic: author-email
Dynamic: classifier
Dynamic: description
Dynamic: description-content-type
Dynamic: home-page
Dynamic: requires-dist
Dynamic: requires-python
Dynamic: summary
